maq_rai_sdk/__init__.py
maq_rai_sdk/_client.py
maq_rai_sdk/_configuration.py
maq_rai_sdk/_patch.py
maq_rai_sdk/py.typed
maq_rai_sdk/_utils/__init__.py
maq_rai_sdk/_utils/serialization.py
maq_rai_sdk/aio/__init__.py
maq_rai_sdk/aio/_client.py
maq_rai_sdk/aio/_configuration.py
maq_rai_sdk/aio/_patch.py
maq_rai_sdk/aio/operations/__init__.py
maq_rai_sdk/aio/operations/_operations.py
maq_rai_sdk/aio/operations/_patch.py
maq_rai_sdk/operations/__init__.py
maq_rai_sdk/operations/_operations.py
maq_rai_sdk/operations/_patch.py
maq_rai_sdk_v1-1.0.0.dist-info/licenses/LICENSE
maq_rai_sdk_v1-1.0.0.dist-info/METADATA
maq_rai_sdk_v1-1.0.0.dist-info/WHEEL
maq_rai_sdk_v1-1.0.0.dist-info/top_level.txt
maq_rai_sdk_v1-1.0.0.dist-info/RECORD
