Metadata-Version: 2.4
Name: maq-rai-sdk-v1
Version: 1.0.0
Summary: Azure functions SDK for reviewing and updating prompts with MAQ RAI
Author-email: MAQ Software <customersuccess@maqsoftware.com>
Maintainer-email: MAQ Software <customersuccess@maqsoftware.com>
License: MIT
Project-URL: Homepage, https://github.com/DivyanshuMaq/maq-rai-sdk-v1
Project-URL: Repository, https://github.com/DivyanshuMaq/maq-rai-sdk-v1.git
Project-URL: Documentation, https://github.com/DivyanshuMaq/maq-rai-sdk-v1#readme
Project-URL: Bug Tracker, https://github.com/DivyanshuMaq/maq-rai-sdk-v1/issues
Keywords: azure,ai,rai,responsible-ai,sdk,maq
Classifier: Development Status :: 4 - Beta
Classifier: Intended Audience :: Developers
Classifier: License :: OSI Approved :: MIT License
Classifier: Operating System :: OS Independent
Classifier: Programming Language :: Python
Classifier: Programming Language :: Python :: 3
Classifier: Programming Language :: Python :: 3.8
Classifier: Programming Language :: Python :: 3.9
Classifier: Programming Language :: Python :: 3.10
Classifier: Programming Language :: Python :: 3.11
Classifier: Programming Language :: Python :: 3.12
Classifier: Topic :: Software Development :: Libraries :: Python Modules
Classifier: Topic :: Internet :: WWW/HTTP
Classifier: Topic :: Scientific/Engineering :: Artificial Intelligence
Requires-Python: >=3.8
License-File: LICENSE
Requires-Dist: azure-core>=1.24.0
Requires-Dist: azure-core-experimental>=1.0.0b1
Requires-Dist: typing-extensions>=4.0.0
Provides-Extra: dev
Requires-Dist: pytest>=7.0.0; extra == "dev"
Requires-Dist: pytest-asyncio>=0.20.0; extra == "dev"
Requires-Dist: pytest-cov>=4.0.0; extra == "dev"
Requires-Dist: black>=22.0.0; extra == "dev"
Requires-Dist: isort>=5.10.0; extra == "dev"
Requires-Dist: mypy>=1.0.0; extra == "dev"
Requires-Dist: flake8>=5.0.0; extra == "dev"
Dynamic: license-file
